learning_assistant/__init__.py
learning_assistant/admin.py
learning_assistant/api.py
learning_assistant/apps.py
learning_assistant/constants.py
learning_assistant/data.py
learning_assistant/models.py
learning_assistant/platform_imports.py
learning_assistant/plugins.py
learning_assistant/plugins_api.py
learning_assistant/serializers.py
learning_assistant/text_utils.py
learning_assistant/toggles.py
learning_assistant/urls.py
learning_assistant/utils.py
learning_assistant/views.py
learning_assistant/management/__init__.py
learning_assistant/management/commands/__init__.py
learning_assistant/management/commands/retire_user_messages.py
learning_assistant/migrations/0001_initial.py
learning_assistant/migrations/0002_alter_courseprompt_prompt.py
learning_assistant/migrations/0003_courseprompt_json_prompt_content.py
learning_assistant/migrations/0004_remove_courseprompt_prompt.py
learning_assistant/migrations/0005_learningassistantcourseenabled.py
learning_assistant/migrations/0006_delete_courseprompt.py
learning_assistant/migrations/0007_learningassistantmessage.py
learning_assistant/migrations/0008_alter_learningassistantmessage_role.py
learning_assistant/migrations/0009_learningassistantaudittrial.py
learning_assistant/migrations/0010_learningassistantaudittrial_expiration_date.py
learning_assistant/migrations/__init__.py
learning_assistant-4.11.3.dist-info/licenses/LICENSE.txt
learning_assistant-4.11.3.dist-info/METADATA
learning_assistant-4.11.3.dist-info/WHEEL
learning_assistant-4.11.3.dist-info/entry_points.txt
learning_assistant-4.11.3.dist-info/top_level.txt
learning_assistant-4.11.3.dist-info/RECORD
