Metadata-Version: 2.4
Name: learning-assistant
Version: 4.11.3
Summary: Plugin for a learning assistant backend, intended for use within edx-platform
Home-page: https://github.com/openedx/learning-assistant
Author: edX
Author-email: team-cosmonauts@edx.org
License: AGPL 3.0
Keywords: Python edx
Classifier: Development Status :: 3 - Alpha
Classifier: Framework :: Django
Classifier: Framework :: Django :: 3.2
Classifier: Intended Audience :: Developers
Classifier: License :: OSI Approved :: GNU Affero General Public License v3 or later (AGPLv3+)
Classifier: Natural Language :: English
Classifier: Programming Language :: Python :: 3
Classifier: Programming Language :: Python :: 3.12
Requires-Python: >=3.8
License-File: LICENSE.txt
Requires-Dist: Django
Requires-Dist: attrs
Requires-Dist: django-model-utils
Requires-Dist: djangorestframework
Requires-Dist: edx-drf-extensions
Requires-Dist: edx-opaque-keys
Requires-Dist: edx-rest-api-client
Requires-Dist: jinja2
Requires-Dist: optimizely-sdk
Dynamic: author
Dynamic: author-email
Dynamic: classifier
Dynamic: description
Dynamic: home-page
Dynamic: keywords
Dynamic: license
Dynamic: license-file
Dynamic: requires-dist
Dynamic: requires-python
Dynamic: summary
